{
    "playerName": "",
    "scienceCredit": 0,
    "planetsInterrupted": [
        {
            "planetId": -1194127123,
            "depletedNodes": [
                -35574241121293,
                -35574241121107,
                -35574241120332,
                -35574241120115,
                -35574241120022,
                -35574241119278,
                -35574241119154,
                -35574241118286,
                -35574241118255,
                -35574241117418,
                -35574241117325,
                -35574241116302,
                -35574241115434,
                -35574241115217,
                -35574241113357
            ]
        }
    ],
    "lastWorld": -1194127123,
    "checksum": "2B796FE3728E642B0270E823C33D42A3D89B33320B5AACE59B8055DE5C8D045B"
}